{
  "dataset": "TEINA230",
  "description": "General government gross debt, % of GDP (quarterly) (latest period)",
  "source_url": "https://ec.europa.eu/eurostat/api/dissemination/statistics/1.0/data/teina230?lastTimePeriod=12",
  "updated_at": "2025-12-08T15:22:47.652409+00:00",
  "latest_period": "2025-Q2",
  "unit": "% of GDP",
  "records": [
    {
      "country_code": "EL",
      "country": "Greece",
      "time": "2025-Q2",
      "value_pct_gdp": 151.2
    },
    {
      "country_code": "IT",
      "country": "Italy",
      "time": "2025-Q2",
      "value_pct_gdp": 138.3
    },
    {
      "country_code": "FR",
      "country": "France",
      "time": "2025-Q2",
      "value_pct_gdp": 115.8
    },
    {
      "country_code": "BE",
      "country": "Belgium",
      "time": "2025-Q2",
      "value_pct_gdp": 106.2
    },
    {
      "country_code": "ES",
      "country": "Spain",
      "time": "2025-Q2",
      "value_pct_gdp": 103.4
    },
    {
      "country_code": "PT",
      "country": "Portugal",
      "time": "2025-Q2",
      "value_pct_gdp": 96.8
    },
    {
      "country_code": "FI",
      "country": "Finland",
      "time": "2025-Q2",
      "value_pct_gdp": 88.4
    },
    {
      "country_code": "EA20",
      "country": "Euro area – 20 countries (from 2023)",
      "time": "2025-Q2",
      "value_pct_gdp": 88.2
    },
    {
      "country_code": "AT",
      "country": "Austria",
      "time": "2025-Q2",
      "value_pct_gdp": 82.3
    },
    {
      "country_code": "EU27_2020",
      "country": "European Union - 27 countries (from 2020)",
      "time": "2025-Q2",
      "value_pct_gdp": 81.9
    },
    {
      "country_code": "HU",
      "country": "Hungary",
      "time": "2025-Q2",
      "value_pct_gdp": 76.2
    },
    {
      "country_code": "SI",
      "country": "Slovenia",
      "time": "2025-Q2",
      "value_pct_gdp": 69.4
    },
    {
      "country_code": "SK",
      "country": "Slovakia",
      "time": "2025-Q2",
      "value_pct_gdp": 62.9
    },
    {
      "country_code": "DE",
      "country": "Germany",
      "time": "2025-Q2",
      "value_pct_gdp": 62.4
    },
    {
      "country_code": "CY",
      "country": "Cyprus",
      "time": "2025-Q2",
      "value_pct_gdp": 61.2
    },
    {
      "country_code": "PL",
      "country": "Poland",
      "time": "2025-Q2",
      "value_pct_gdp": 58.1
    },
    {
      "country_code": "HR",
      "country": "Croatia",
      "time": "2025-Q2",
      "value_pct_gdp": 57.5
    },
    {
      "country_code": "RO",
      "country": "Romania",
      "time": "2025-Q2",
      "value_pct_gdp": 57.3
    },
    {
      "country_code": "LV",
      "country": "Latvia",
      "time": "2025-Q2",
      "value_pct_gdp": 48.0
    },
    {
      "country_code": "MT",
      "country": "Malta",
      "time": "2025-Q2",
      "value_pct_gdp": 46.9
    },
    {
      "country_code": "CZ",
      "country": "Czechia",
      "time": "2025-Q2",
      "value_pct_gdp": 43.8
    },
    {
      "country_code": "NO",
      "country": "Norway",
      "time": "2025-Q2",
      "value_pct_gdp": 43.2
    },
    {
      "country_code": "NL",
      "country": "Netherlands",
      "time": "2025-Q2",
      "value_pct_gdp": 42.7
    },
    {
      "country_code": "LT",
      "country": "Lithuania",
      "time": "2025-Q2",
      "value_pct_gdp": 39.1
    },
    {
      "country_code": "SE",
      "country": "Sweden",
      "time": "2025-Q2",
      "value_pct_gdp": 34.0
    },
    {
      "country_code": "IE",
      "country": "Ireland",
      "time": "2025-Q2",
      "value_pct_gdp": 33.3
    },
    {
      "country_code": "DK",
      "country": "Denmark",
      "time": "2025-Q2",
      "value_pct_gdp": 29.7
    },
    {
      "country_code": "BG",
      "country": "Bulgaria",
      "time": "2025-Q2",
      "value_pct_gdp": 26.3
    },
    {
      "country_code": "LU",
      "country": "Luxembourg",
      "time": "2025-Q2",
      "value_pct_gdp": 25.1
    },
    {
      "country_code": "EE",
      "country": "Estonia",
      "time": "2025-Q2",
      "value_pct_gdp": 23.2
    }
  ],
  "notes": [
    "Eurostat 1.0 API; 12 quarters retrieved and reduced to latest quarter in ETL.",
    "Values represent consolidated gross debt of general government.",
    "Figures may be revised by Eurostat; check source for metadata."
  ]
}